enthusiast_model_ollama/__init__.py
enthusiast_model_ollama/embedding.py
enthusiast_model_ollama/language_model.py
enthusiast_model_ollama-1.2.0.dist-info/METADATA
enthusiast_model_ollama-1.2.0.dist-info/WHEEL
enthusiast_model_ollama-1.2.0.dist-info/RECORD
