Metadata-Version: 2.4
Name: enthusiast-model-ollama
Version: 1.2.0
Summary: A plugin for Enthusiast that provides an Ollama connector.
Author: Rafal Cymerys
Author-email: rafal@upsidelab.io
Requires-Python: >=3.12,<4.0
Classifier: Programming Language :: Python :: 3
Classifier: Programming Language :: Python :: 3.12
Classifier: Programming Language :: Python :: 3.13
Classifier: Programming Language :: Python :: 3.14
Requires-Dist: enthusiast-common (>=1,<2)
Requires-Dist: langchain-core (>=0.3.66,<0.4.0)
Requires-Dist: langchain-ollama (>=0.3.3,<0.4.0)
